simple_plugins.py
simple_plugins-1.0.3.dist-info/AUTHORS
simple_plugins-1.0.3.dist-info/LICENSE
simple_plugins-1.0.3.dist-info/METADATA
simple_plugins-1.0.3.dist-info/WHEEL
simple_plugins-1.0.3.dist-info/top_level.txt
simple_plugins-1.0.3.dist-info/RECORD
