Metadata-Version: 2.1
Name: simple-plugins
Version: 1.0.3
Summary: A simple plugin framework
Home-page: https://github.com/petarmaric/simple_plugins
Author: Petar Maric
Author-email: petarmaric@uns.ac.rs
License: BSD
Platform: any
Classifier: Development Status :: 5 - Production/Stable
Classifier: Intended Audience :: Developers
Classifier: License :: OSI Approved :: BSD License
Classifier: Operating System :: OS Independent
Classifier: Programming Language :: Python :: 2.6
Classifier: Programming Language :: Python :: 2.7
Classifier: Topic :: Software Development
Classifier: Topic :: Utilities
